[{"level":4,"theme":"Elated","words":["ELATED","JUBILANT","DELIGHTED","CHEERFUL","UPBEAT"]},{"level":4,"theme":"Mournful","words":["MOURNFUL","SOMBRE","GLOOMY","SORROWFUL","DOWNCAST"]},{"level":4,"theme":"Irate","words":["IRATE","LIVID","FURIOUS","ENRAGED","INCENSED"]},{"level":4,"theme":"Anxious","words":["ANXIOUS","UNEASY","FEARFUL","ALARMED","STARTLED"]},{"level":4,"theme":"Valiant","words":["VALIANT","HEROIC","GALLANT","DARING","COURAGEOUS"]},{"level":4,"theme":"Astute","words":["ASTUTE","CLEVER","SHREWD","BRIGHT","INSIGHTFUL"]},{"level":4,"theme":"Absurd","words":["ABSURD","FOOLISH","RIDICULOUS","SENSELESS","INANE"]},{"level":4,"theme":"Rapid","words":["RAPID","SWIFT","BRISK","SPEEDY","FLEET"]},{"level":4,"theme":"Sluggish","words":["SLUGGISH","GRADUAL","PLODDING","DELAYED","UNHURRIED"]},{"level":4,"theme":"Enormous","words":["ENORMOUS","IMMENSE","COLOSSAL","GIGANTIC","VAST"]},{"level":4,"theme":"Miniature","words":["MINIATURE","COMPACT","PETITE","TINY","MINUTE"]},{"level":4,"theme":"Elegant","words":["ELEGANT","GORGEOUS","RADIANT","GRACEFUL","EXQUISITE"]},{"level":4,"theme":"Grotesque","words":["GROTESQUE","HIDEOUS","REPULSIVE","UNSIGHTLY","GHASTLY"]},{"level":4,"theme":"Affluent","words":["AFFLUENT","WEALTHY","PROSPEROUS","OPULENT","LOADED"]},{"level":4,"theme":"Destitute","words":["DESTITUTE","PENNILESS","NEEDY","DEPRIVED","IMPOVERISHED"]},{"level":4,"theme":"Hushed","words":["HUSHED","SILENT","MUTED","SUBDUED","TRANQUIL"]},{"level":4,"theme":"Deafening","words":["DEAFENING","BOOMING","THUNDEROUS","BLARING","CLAMOROUS"]},{"level":4,"theme":"Weary","words":["WEARY","FATIGUED","DRAINED","EXHAUSTED","SPENT"]},{"level":4,"theme":"Robust","words":["ROBUST","STURDY","MIGHTY","POWERFUL","FORMIDABLE"]},{"level":4,"theme":"Fragile","words":["FRAGILE","FEEBLE","FRAIL","INFIRM","POWERLESS"]},{"level":4,"theme":"Pristine","words":["PRISTINE","SPOTLESS","IMMACULATE","PURE","POLISHED"]},{"level":4,"theme":"Grimy","words":["GRIMY","FILTHY","SOILED","STAINED","POLLUTED"]},{"level":4,"theme":"Ancient","words":["ANCIENT","ARCHAIC","ELDERLY","VENERABLE","AGED"]},{"level":4,"theme":"Novel","words":["NOVEL","MODERN","RECENT","CURRENT","FRESH"]},{"level":4,"theme":"Generous","words":["GENEROUS","GRACIOUS","HUMANE","CARING","BENEVOLENT"]},{"level":4,"theme":"Ruthless","words":["RUTHLESS","VICIOUS","BRUTAL","MERCILESS","HARSH"]},{"level":4,"theme":"Candid","words":["CANDID","SINCERE","TRUTHFUL","GENUINE","FRANK"]},{"level":4,"theme":"Deceptive","words":["DECEPTIVE","BOGUS","FRAUDULENT","PHONY","UNTRUE"]},{"level":4,"theme":"Witty","words":["WITTY","HUMOROUS","COMICAL","AMUSING","HILARIOUS"]},{"level":4,"theme":"Solemn","words":["SOLEMN","EARNEST","GRAVE","SOMBRE","STERN"]},{"level":4,"theme":"Effortless","words":["EFFORTLESS","SIMPLE","PAINLESS","BASIC","PLAIN"]},{"level":4,"theme":"Arduous","words":["ARDUOUS","COMPLEX","DEMANDING","DIFFICULT","TAXING"]},{"level":4,"theme":"Crucial","words":["CRUCIAL","VITAL","PIVOTAL","ESSENTIAL","MAJOR"]},{"level":4,"theme":"Bizarre","words":["BIZARRE","PECULIAR","UNUSUAL","ODD","STRANGE"]},{"level":4,"theme":"Customary","words":["CUSTOMARY","TYPICAL","STANDARD","ORDINARY","USUAL"]},{"level":4,"theme":"Hazardous","words":["HAZARDOUS","PERILOUS","RISKY","UNSAFE","TREACHEROUS"]},{"level":4,"theme":"Sheltered","words":["SHELTERED","SECURE","PROTECTED","GUARDED","HARMLESS"]},{"level":4,"theme":"Luminous","words":["LUMINOUS","RADIANT","VIVID","BRILLIANT","GLOWING"]},{"level":4,"theme":"Murky","words":["MURKY","SHADOWY","GLOOMY","DIM","DUSKY"]},{"level":4,"theme":"Scorching","words":["SCORCHING","SWELTERING","SEARING","BOILING","BLISTERING"]},{"level":4,"theme":"Frigid","words":["FRIGID","FREEZING","ICY","FROSTY","BITTER"]},{"level":4,"theme":"Ravenous","words":["RAVENOUS","FAMISHED","STARVING","PECKISH","HOLLOW"]},{"level":4,"theme":"Satiated","words":["SATIATED","STUFFED","FILLED","PACKED","SATISFIED"]},{"level":4,"theme":"Vacant","words":["VACANT","HOLLOW","BARREN","BARE","DESERTED"]},{"level":4,"theme":"Congested","words":["CONGESTED","PACKED","CRAMPED","THRONGED","CROWDED"]},{"level":4,"theme":"Lethargic","words":["LETHARGIC","IDLE","SLUGGISH","INACTIVE","INDOLENT"]},{"level":4,"theme":"Bustling","words":["BUSTLING","ACTIVE","OCCUPIED","ENGAGED","INDUSTRIOUS"]},{"level":4,"theme":"Insolent","words":["INSOLENT","IMPOLITE","OFFENSIVE","CRUDE","DISRESPECTFUL"]},{"level":4,"theme":"Courteous","words":["COURTEOUS","GRACIOUS","CIVIL","RESPECTFUL","WELLMANNERED"]},{"level":4,"theme":"Serene","words":["SERENE","TRANQUIL","COMPOSED","PEACEFUL","RELAXED"]},{"level":4,"theme":"Untamed","words":["UNTAMED","SAVAGE","FERAL","RECKLESS","FIERCE"]},{"level":4,"theme":"Vigilant","words":["VIGILANT","CAUTIOUS","WARY","WATCHFUL","ALERT"]},{"level":4,"theme":"Negligent","words":["NEGLIGENT","RECKLESS","SLOPPY","CARELESS","HASTY"]},{"level":4,"theme":"Tedious","words":["TEDIOUS","DULL","DREARY","MONOTONOUS","TIRESOME"]},{"level":4,"theme":"Thrilling","words":["THRILLING","GRIPPING","LIVELY","DRAMATIC","RIVETING"]},{"level":4,"theme":"Renowned","words":["RENOWNED","NOTABLE","CELEBRATED","EMINENT","ACCLAIMED"]},{"level":4,"theme":"Concealed","words":["CONCEALED","DISGUISED","VEILED","HIDDEN","SECRET"]},{"level":4,"theme":"Evident","words":["EVIDENT","APPARENT","OBVIOUS","VISIBLE","PLAIN"]},{"level":4,"theme":"Bewildered","words":["BEWILDERED","BAFFLED","PUZZLED","CONFUSED","UNCERTAIN"]},{"level":4,"theme":"Assured","words":["ASSURED","DEFINITE","CONFIDENT","CERTAIN","POSITIVE"]},{"level":4,"theme":"Fortunate","words":["FORTUNATE","FAVOURED","BLESSED","CHARMED","LUCKY"]},{"level":4,"theme":"Hapless","words":["HAPLESS","UNFORTUNATE","CURSED","DOOMED","LUCKLESS"]},{"level":4,"theme":"Orderly","words":["ORDERLY","TIDY","ORGANISED","IMMACULATE","NEAT"]},{"level":4,"theme":"Chaotic","words":["CHAOTIC","CLUTTERED","UNTIDY","DISORDERED","MESSY"]},{"level":4,"theme":"Jagged","words":["JAGGED","POINTED","ACUTE","KEEN","SHARP"]},{"level":4,"theme":"Rounded","words":["ROUNDED","BLUNT","DULL","FLAT","POINTLESS"]},{"level":4,"theme":"Tender","words":["TENDER","DELICATE","GENTLE","SMOOTH","MILD"]},{"level":4,"theme":"Abrasive","words":["ABRASIVE","RUGGED","COARSE","UNEVEN","HARSH"]},{"level":4,"theme":"Saturated","words":["SATURATED","SOAKED","SOGGY","DAMP","MOIST"]},{"level":4,"theme":"Desiccated","words":["DESICCATED","PARCHED","ARID","CRISP","WATERLESS"]},{"level":4,"theme":"Slender","words":["SLENDER","NARROW","LEAN","SLIM","THIN"]},{"level":4,"theme":"Dense","words":["DENSE","BULKY","BROAD","CHUNKY","THICK"]},{"level":4,"theme":"Premature","words":["PREMATURE","PROMPT","TIMELY","ADVANCED","EARLY"]},{"level":4,"theme":"Belated","words":["BELATED","OVERDUE","DELAYED","TARDY","LATE"]},{"level":4,"theme":"Adjacent","words":["ADJACENT","PROXIMATE","NEARBY","NEIGHBOURING","CLOSE"]},{"level":4,"theme":"Remote","words":["REMOTE","DISTANT","FARAWAY","REMOVED","ISOLATED"]},{"level":4,"theme":"Commence","words":["COMMENCE","INITIATE","LAUNCH","BEGIN","START"]},{"level":4,"theme":"Conclude","words":["CONCLUDE","TERMINATE","CEASE","FINISH","COMPLETE"]},{"level":4,"theme":"Construct","words":["CONSTRUCT","ASSEMBLE","PRODUCE","FORGE","CREATE"]},{"level":4,"theme":"Fracture","words":["FRACTURE","SHATTER","RUPTURE","SMASH","DESTROY"]},{"level":4,"theme":"Restore","words":["RESTORE","REPAIR","MEND","RECTIFY","CORRECT"]},{"level":4,"theme":"Relocate","words":["RELOCATE","TRANSFER","DISPLACE","SHIFT","MOVE"]},{"level":4,"theme":"Propel","words":["PROPEL","FLING","HURL","TOSS","LAUNCH"]},{"level":4,"theme":"Seize","words":["SEIZE","CLUTCH","GRASP","SNATCH","GRAB"]},{"level":4,"theme":"Observe","words":["OBSERVE","INSPECT","GAZE","STARE","WATCH"]},{"level":4,"theme":"Declare","words":["DECLARE","EXPRESS","ANNOUNCE","UTTER","STATE"]},{"level":4,"theme":"Bellow","words":["BELLOW","ROAR","HOLLER","YELL","SCREAM"]},{"level":4,"theme":"Murmur","words":["MURMUR","MUMBLE","MUTTER","WHISPER","BREATHE"]},{"level":4,"theme":"Assist","words":["ASSIST","SUPPORT","AID","ENCOURAGE","FACILITATE"]},{"level":4,"theme":"Injure","words":["INJURE","WOUND","DAMAGE","HARM","IMPAIR"]},{"level":4,"theme":"Cherish","words":["CHERISH","ADORE","TREASURE","REVERE","VALUE"]},{"level":4,"theme":"Loathe","words":["LOATHE","DETEST","DESPISE","ABHOR","DISLIKE"]},{"level":4,"theme":"Desire","words":["DESIRE","CRAVE","COVET","YEARN","SEEK"]},{"level":4,"theme":"Ponder","words":["PONDER","REFLECT","CONSIDER","REASON","CONTEMPLATE"]},{"level":4,"theme":"Select","words":["SELECT","ELECT","DECIDE","NOMINATE","CHOOSE"]},{"level":4,"theme":"Discover","words":["DISCOVER","DETECT","LOCATE","UNCOVER","FIND"]},{"level":4,"theme":"Obscure","words":["OBSCURE","CONCEAL","DISGUISE","MASK","HIDE"]},{"level":4,"theme":"Triumph","words":["TRIUMPH","PREVAIL","CONQUER","SUCCEED","WIN"]},{"level":4,"theme":"Forfeit","words":["FORFEIT","SURRENDER","MISPLACE","FAIL","LOSE"]},{"level":4,"theme":"Exhibit","words":["EXHIBIT","REVEAL","DISPLAY","EXPOSE","PRESENT"]}]